32_furry/core.v
module core
(
    // --- УПРАВЛЯЮЩИЕ
    input               clock,      // 25Мгц
    input               rst_n,      // =0 Сброс процессора
    input               ce,         // =1 Активация чипа
    output              m0,         // Первый такт
    // --- ПАМЯТЬ
    output      [31:0]  a,          // Адрес в общей памяти
    input       [ 7:0]  i,          // Данные из памяти
    output reg  [ 7:0]  o,          // Данные в память
    output reg          w,          // Запись в память,
    // --- РЕГИСТРЫ
    output reg  [31:0]  eax,
    output reg  [31:0]  ebx,
    output reg  [31:0]  ecx,
    output reg  [31:0]  edx,
    output reg  [31:0]  esp,
    output reg  [31:0]  ebp,
    output reg  [31:0]  esi,
    output reg  [31:0]  edi,
    // --- СЕГМЕНТЫ
    output reg  [15:0]  es,
    output reg  [15:0]  cs,
    output reg  [15:0]  ss,
    output reg  [15:0]  ds,
    // --- УПРАВЛЯЮЩИЕ
    output reg  [31:0]  eip,
    output reg  [11:0]  flags,
    // --- ИНИЦИАЛИЗАЦИЯ
    input       [31:0]  _eax,
    input       [31:0]  _ebx,
    input       [31:0]  _ecx,
    input       [31:0]  _edx,
    input       [31:0]  _esp,
    input       [31:0]  _ebp,
    input       [31:0]  _esi,
    input       [31:0]  _edi,
    input       [15:0]  _es,
    input       [15:0]  _cs,
    input       [15:0]  _ss,
    input       [15:0]  _ds,
    input       [31:0]  _eip,
    input       [11:0]  _flags
);

assign a = cp ? sgn*16 + ea : cs*16 + eip;

localparam
    RUN         = 0, // Исполнение
    MODRM       = 1, // Разбор операндов
    WB          = 2, // Запись результата
    PUSH        = 3, // Запись wb в стек
    POP         = 4, // Чтение из стека -> wb
    DIV         = 5, // Деление op1/op2
    INTERRUPT   = 6, // Вызов прерывания
    UNDEF       = 7; // Ошибка опкода

localparam ADD = 0, OR  = 1, ADC = 2, SBB  = 3, AND = 4, SUB = 5, XOR = 6, CMP = 7;
localparam ROL = 0, ROR = 1, RCL = 2, RCR  = 3, SHL = 4, SHR = 5, SAL = 6, SAR = 7;
localparam CF  = 0, PF  = 2, AF  = 4, ZF   = 6, SF  = 7, TF  = 8, IF  = 9, DF  = 10, OF = 11;

// -----------------------------------------------------
`define CPEN cp <= cpen; if (!cpen) begin m1 <= 0; t <= RUN; end
`define TERM {m, rep, over, sgn} <= ds;
// Если эта процедура является завершающей, так как переход идет на RUN
`define TERM_FN if (next == RUN && !m) `TERM
// -----------------------------------------------------
reg         cp;                     // =1 Указатель на SGN:EA =0 Иначе CS:IP
reg         cpm;                    // =0 Устанавливается cp после MODRM
reg         size;                   // =1 16bit =0 8bit
reg         dir;                    // =0 rm,r; =1 r,rm
reg         cpen;                   // =0 То пропускает чтение операндов
reg         over;                   // =1 Сегмент переопределен
reg         intrc;                  // Предыдущее значение intr
reg [ 1:0]  rep;                    // Наличие REP:
reg [ 3:0]  t, next;                // Исполняемая команда (t) в данный момент
reg [ 3:0]  m, m1;                  // Фаза исполнения T (m), MODRM и субфаза
reg [ 2:0]  m2, m3, m4;             // Фаза исполнения WB, PUSH/POP
reg [ 2:0]  alu;                    // Функция АЛУ или сдвигов
reg [ 7:0]  modrm, sib, opcache;    // Кешированные значения
reg [ 7:0]  interrupt;              // Номер прерывания
reg [31:0]  sgn, ea;                // Выбранный SEGMENT:EA
reg [31:0]  op1, op2, wb, t16;      // Операнды; wb-что записывать
reg         op66, op67;             // Расширение операндов и адреса
// -----------------------------------------------------
assign      m0 = (t == RUN && m == 0);
wire        c0 = m0 && {over, rep} == 3'b0;
wire [7:0]  opcode = m || t ? opcache : i;
// -----------------------------------------------------
wire [255:0] u20 = {edi, esi, ebp, esp, ebx, edx, ecx, eax};
// ----
wire [ 31:0] r20 = u20 >> {i[2:0], 5'b0};
wire [ 31:0] r53 = u20 >> {i[5:3], 5'b0};
wire [  7:0] s20 = u20 >> {i[1:0], 1'b0, i[2], 3'b0};
wire [  7:0] s53 = u20 >> {i[4:3], 1'b0, i[5], 3'b0};
// ----
wire [ 31:0] i20 = size ? (op66 ? r20 : r20[15:0]) : s20;
wire [ 31:0] i53 = size ? (op66 ? r53 : r53[15:0]) : s53;
// ----
wire [ 31:0] sign = {{24{i[7]}}, i};
wire [ 31:0] eipn = eip + 1'b1;
wire [ 31:0] ean  = ea  + 1'b1;
// -----------------------------------------------------
wire [4:0]  top = size ? (op66 ? 31 : 15) : 7;
wire [32:0] ar =
    alu == ADD ? op1 + op2 :
    alu == ADC ? op1 + op2 + flags[CF] :
    alu == SBB ? op1 - op2 - flags[CF] :
    alu == AND ? op1 & op2 :
    alu == XOR ? op1 ^ op2 :
    alu == OR  ? op1 | op2 : op1 - op2;

wire isa    = alu == ADD || alu == ADC;
wire isl    = alu != AND && alu != OR && alu != XOR;
wire new_o  = (op1[top] ^ op2[top] ^ isa) & (op1[top] ^ ar[top]);
wire new_s  = ar[top];
wire new_z  = 0 == (size ? ar[15:0] : ar[7:0]);
wire new_a  = op1[4] ^ op2[4] ^ ar[4];
wire new_p  = ~^ar[7:0];
wire new_c  = ar[top + 1];

wire [11:0] af = {new_o & isl, flags[10:8], new_s, new_z, 1'b0, new_a & isl, 1'b0, new_p, 1'b1, new_c & isl};
// -----------------------------------------------------

always @(posedge clock)
// Сброс процессора
if (rst_n == 0) begin

    t  <= RUN;
    m  <= 0;
    cp <= 0;

    // Копирование первоначальных значений при сбросе
    eax <= _eax; ebx <= _ebx; ecx <= _ecx; edx <= _edx;
    esp <= _esp; ebp <= _ebp; esi <= _esi; edi <= _edi;

    es  <= _es;
    cs  <= _cs;
    ss  <= _ss;
    ds  <= _ds;

    eip   <= _eip;
    flags <= _flags;

// Запуск выполнения команд процессора
end
else if (ce) begin

    w <= 0;

    // Очистить управляющие регистры в начале инструкции
    if (m0) begin

        next    <= RUN;
        eip     <= eipn;
        op66    <= 1;
        op67    <= 1;
        m       <= 1;
        m1      <= 0;
        m2      <= 0;
        m3      <= 0;
        m4      <= 0;
        cpm     <= 1;
        cpen    <= 1;
        opcache <= i;
        dir     <= i[1];
        size    <= i[0];

        if (c0) sgn <= ds;

    end

    case (t)

    // ИСПОЛНЕНИЕ ИНСТРУКЦИИ
    RUN: casex (opcode)

        // ### ALU-операции с операндами ModRM [3T+]
        8'b00xxx0xx: case (m)

            0: begin t <= MODRM; alu <= opcode[5:3]; end
            1: begin

                m     <= 0;
                t     <= alu == CMP ? RUN : WB;
                wb    <= ar;
                flags <= af;

                if (alu == CMP) `TERM;

            end

        endcase

        // ### Префикс ES/CS/SS/DS [1T]
        8'b00100110: begin m <= 0; over <= 1; sgn <= es; end
        8'b00101110: begin m <= 0; over <= 1; sgn <= cs; end
        8'b00110110: begin m <= 0; over <= 1; sgn <= ss; end
        8'b00111110: begin m <= 0; over <= 1; sgn <= ds; end

        // ### Opsize, Adsize
        8'b01100110: begin m <= 0; op66 <= ~op66; end
        8'b01100111: begin m <= 0; op67 <= ~op67; end

        // ### REPNZ, REPZ [1T]
        8'b1111001x: begin m <= 0; rep <= i[1:0]; end

    endcase

    // СЧИТЫВАНИЕ ОПЕРАНДОВ ИЗ РЕГИСТРОВ ИЛИ ИЗ ПАМЯТИ
    MODRM: case (m1)

        // Разбор 16/32 эффективного адреса и регистров при необходимости
        0: begin

            modrm   <= i;
            eip     <= eipn;
            op1     <= dir ? i53 : i20;
            op2     <= dir ? i20 : i53;

            if (op67) begin

                ea <= i20;

                // Эффективный 32-х битный адрес
                casex (i)
                8'b00_xxx_100: begin m1 <= 10; end          // SIB
                8'b00_xxx_101: begin ea <= 0; m2 <= 2;  end // A32
                8'b01_xxx_101: begin m1 <= 1; if (!over) sgn <= ss; end
                8'b10_xxx_101: begin m1 <= 2; if (!over) sgn <= ss; end
                8'b01_xxx_xxx: begin m1 <= 1; end           // +D8
                8'b10_xxx_xxx: begin m1 <= 2; end           // +32
                8'b11_xxx_xxx: begin m1 <= 0; t <= RUN; end
                endcase

            end else begin

                // Вычислить эффективный 16-битный адрес
                case (i[2:0])
                3'b000: ea <= ebx[15:0] + esi[15:0];
                3'b001: ea <= ebx[15:0] + edi[15:0];
                3'b010: ea <= ebp[15:0] + esi[15:0];
                3'b011: ea <= ebp[15:0] + edi[15:0];
                3'b100: ea <= esi[15:0];
                3'b101: ea <= edi[15:0];
                3'b110: ea <= i[7:6] ? ebp[15:0] : 0;
                3'b111: ea <= ebx[15:0];
                endcase

                // Возможные 16-битные смещения
                casex (i)
                8'b00_xxx_110: begin m1 <= 2; end           // OFFSET16
                8'b00_xxx_xxx: begin m1 <= 6; `CPEN; end    // Читать операнд
                8'b01_xxx_xxx: begin m1 <= 1; end           // +Смещение 8 бит
                8'b10_xxx_xxx: begin m1 <= 2; end           // +Смещение 16 бит
                8'b11_xxx_xxx: begin m1 <= 0; t <= RUN; end // Регистры. Вернуться к RUN
                endcase

                if (!over && ((^i[7:6] && i[2:0] == 3'b110) || i[2:1] == 2'b01)) sgn <= ss;

            end

        end

        // DISP8
        1: begin m1 <= 4; eip <= eipn; ea <= ea + sign; `CPEN; end

        // DISP16/32
        2: begin m1 <= 3; eip <= eipn; ea <= ea + {8'b0, i}; end
        3: begin m1 <= 4; eip <= eipn; ea <= ea + {i, 8'b0}; if (op67) m1 <= 4; else begin `CPEN; end end
        4: begin m1 <= 5; eip <= eipn; ea <= ea + {i, 16'b0}; end
        5: begin m1 <= 0; eip <= eipn; ea <= ea + {i, 24'b0}; `CPEN; end

        // Читать 8-битный операнд
        6: begin

            if (dir) op2 <= i; else op1 <= i;
            if (size) begin m1 <= 5; ea <= ean; end
            else      begin m1 <= 0; cp <= cpm; t <= RUN; end

        end

        // Читать 16-битный операнд
        7: begin

            if (dir) op2[15:8] <= i; else op1[15:8] <= i;

            if (op67) m1 <= 8;
            else begin

                t  <= RUN;
                m1 <= 0;
                ea <= ea - 1;
                cp <= cpm;

            end

        end

        // Читать операнд 32-х бит
        8: begin m1 <= 9; if (dir) op2[23:16] <= i; else op1[23:16] <= i; end
        9: begin

            if (dir) op2[31:24] <= i; else op1[31:24] <= i;

            t  <= RUN;
            m1 <= 0;
            ea <= ea - 3;
            cp <= cpm;

        end

        // SIB
        10: begin end

    endcase

    // [1T,2-3T] ЗАПИСЬ РЕЗУЛЬТАТОВ WB,DIR,SIZE,MODRM В ПАМЯТЬ/РЕГИСТРЫ
    WB: case (m2)

        // Записать в регистры, если это явно указано
        0: if (dir || modrm[7:6] == 2'b11) begin

            t  <= next;
            cp <= 0;

            casex ({op66, size, dir ? modrm[5:3] : modrm[2:0]})
            // 8
            5'b00_000: eax[ 7:0] <= wb[7:0];
            5'b00_001: ecx[ 7:0] <= wb[7:0];
            5'b00_010: edx[ 7:0] <= wb[7:0];
            5'b00_011: ebx[ 7:0] <= wb[7:0];
            5'b00_100: eax[15:8] <= wb[7:0];
            5'b00_101: ecx[15:8] <= wb[7:0];
            5'b00_110: edx[15:8] <= wb[7:0];
            5'b00_111: ebx[15:8] <= wb[7:0];
            // 16
            5'b01_000: eax[15:0] <= wb[15:0];
            5'b01_001: ecx[15:0] <= wb[15:0];
            5'b01_010: edx[15:0] <= wb[15:0];
            5'b01_011: ebx[15:0] <= wb[15:0];
            5'b01_100: esp[15:0] <= wb[15:0];
            5'b01_101: ebp[15:0] <= wb[15:0];
            5'b01_110: esi[15:0] <= wb[15:0];
            5'b01_111: edi[15:0] <= wb[15:0];
            // 32
            5'b1x_000: eax <= wb;
            5'b1x_001: ecx <= wb;
            5'b1x_010: edx <= wb;
            5'b1x_011: ebx <= wb;
            5'b1x_100: esp <= wb;
            5'b1x_101: ebp <= wb;
            5'b1x_110: esi <= wb;
            5'b1x_111: edi <= wb;
            endcase

            `TERM_FN;

        end
        // Либо записать в память младший байт wb
        else begin w <= 1; cp <= 1; m2 <= 1; o <= wb[7:0]; end
        // Старший байт нижнего слова
        1: begin

            o  <= wb[15:8];
            w  <= size;
            ea <= ean;

            if (size && op66) m2 <= 2;
            else if (!size) begin m2 <= 0; cp <= 0; t <= next; `TERM_FN; end

        end
        // Верхнее слово
        2: begin m2 <= 3; w <= 1; o <= wb[23:16]; end
        3: begin m2 <= 4; w <= 1; o <= wb[31:24]; end
        4: begin m2 <= 0; cp <= 0; t <= next; `TERM_FN; end

    endcase // Завершение m2

    // [3T] ВЫГРУЗКА WB -> В СТЕК
    PUSH: case (m3)
    0: begin

        w  <= 1; o   <= wb[ 7:0];
        cp <= 1; esp <= esp - 2; sgn <= ss;
        m3 <= 1; ea  <= esp - 2;

    end
    1: begin o <= wb[15:8];  m3 <= op66 ? 2 : 4; ea <= ean; w <= 1; end
    2: begin o <= wb[23:16]; m3 <= 3; ea <= ean; w <= 1; end
    3: begin o <= wb[31:24]; m3 <= 4; ea <= ean; w <= 1; end
    4: begin `TERM_FN;       m3 <= 0; cp <= 0; t <= next; end
    endcase

    // [3T] ЗАГРУЗКА ИЗ СТЕКА -> WB
    POP: case (m3)
    0: begin m3 <= 1; cp <= 1; sgn <= ss; ea <= esp; esp <= esp + 2; end
    1: begin m3 <= op66 ? 2 : 4; wb <= i; ea <= ean; end
    2: begin m3 <= 3; wb[15:8]  <= i; ea <= ean; end
    3: begin m3 <= 4; wb[23:16] <= i; ea <= ean; end
    4: begin

        t  <= next;
        m3 <= 0;
        cp <= 0;

        if (op66) wb[31:24] <= i; else wb[15:8] <= i;

        `TERM_FN;

    end

    endcase

    // [17T] ВЫЗОВ ПРОЦЕДУРЫ INTERRUPT
    INTERRUPT: case (m4)
    0: begin m4 <= 1; t  <= PUSH; wb <= {4'hF, flags}; next <= INTERRUPT; end
    1: begin m4 <= 2; t  <= PUSH; wb <= cs; end
    2: begin m4 <= 3; t  <= PUSH; wb <= eip; end
    3: begin m4 <= 4; ea <= {interrupt, 2'b00}; sgn <= 0; cp <= 1; end
    4: begin m4 <= 5; eip[ 7:0] <= i; ea <= ean; end
    5: begin m4 <= 6; eip[15:8] <= i; ea <= ean; end
    6: begin m4 <= 7; cs[ 7:0]  <= i; ea <= ean; end
    7: begin m4 <= 0; cs[15:8]  <= i; cp <= 0; t <= RUN; flags[IF] <= 1'b0; m <= 0; `TERM; end
    endcase

    endcase

end

endmodule

32_furry/tb.v
`timescale 10ns / 1ns
module tb;

// --------------------------------
reg clock_25 = 0, clock_100 = 0, rst_n = 0;
// --------------------------------
always #2.0 clock_25  = ~clock_25;
always #0.5 clock_100  = ~clock_100;
// --------------------------------
reg [7:0] mem[1048576];
// --------------------------------
initial begin #4.0 rst_n = 1; #1000 $finish; end
initial begin $dumpfile("tb.vcd"); $dumpvars(0, tb); end
initial begin $readmemh("tb.hex", mem, 20'hFFFF0); end
// --------------------------------
wire [31:0] a;
wire [ 7:0] i = mem[a[19:0]];
wire [ 7:0] o;
wire        w;
// --------------------------------
always @(posedge clock_25) if (w) mem[a[19:0]] <= o;
// --------------------------------

core C1
(
    .clock  (clock_25),
    .rst_n  (rst_n),
    .ce     (1'b1),
    // Подключение к контроллеру памяти
    .a      (a),
    .i      (i),
    .o      (o),
    .w      (w),
    // Первичное значение регистров
    ._eax   (32'h0000),
    ._ebx   (32'h0000),
    ._ecx   (32'h0000),
    ._edx   (32'h0000),
    ._esp   (32'h0000),
    ._ebp   (32'h0000),
    ._esi   (32'h0000),
    ._edi   (32'h0000),
    ._es    (16'hFFFF),
    ._cs    (16'hF000),
    ._ss    (16'hFFFF),
    ._ds    (16'h0000),
    ._eip   (32'hFFF0),
    ._flags (12'b0000_0000_0000)
);

endmodule

32_furry/tb.vcd
$date
	Wed Mar 11 11:21:45 2026
$end
$version
	Icarus Verilog
$end
$timescale
	1ns
$end
$scope module tb $end
$var wire 8 ! i [7:0] $end
$var wire 1 " w $end
$var wire 8 # o [7:0] $end
$var wire 32 $ a [31:0] $end
$var reg 1 % clock_100 $end
$var reg 1 & clock_25 $end
$var reg 1 ' rst_n $end
$scope module C1 $end
$var wire 16 ( _cs [15:0] $end
$var wire 16 ) _ds [15:0] $end
$var wire 32 * _eax [31:0] $end
$var wire 32 + _ebp [31:0] $end
$var wire 32 , _ebx [31:0] $end
$var wire 32 - _ecx [31:0] $end
$var wire 32 . _edi [31:0] $end
$var wire 32 / _edx [31:0] $end
$var wire 32 0 _eip [31:0] $end
$var wire 16 1 _es [15:0] $end
$var wire 32 2 _esi [31:0] $end
$var wire 32 3 _esp [31:0] $end
$var wire 12 4 _flags [11:0] $end
$var wire 16 5 _ss [15:0] $end
$var wire 1 6 c0 $end
$var wire 1 7 ce $end
$var wire 1 & clock $end
$var wire 8 8 i [7:0] $end
$var wire 1 9 isa $end
$var wire 1 : isl $end
$var wire 1 ; m0 $end
$var wire 1 < new_a $end
$var wire 1 = new_o $end
$var wire 1 ' rst_n $end
$var wire 256 > u20 [255:0] $end
$var wire 5 ? top [4:0] $end
$var wire 32 @ sign [31:0] $end
$var wire 8 A s53 [7:0] $end
$var wire 8 B s20 [7:0] $end
$var wire 32 C r53 [31:0] $end
$var wire 32 D r20 [31:0] $end
$var wire 8 E opcode [7:0] $end
$var wire 1 F new_z $end
$var wire 1 G new_s $end
$var wire 1 H new_p $end
$var wire 1 I new_c $end
$var wire 32 J i53 [31:0] $end
$var wire 32 K i20 [31:0] $end
$var wire 32 L eipn [31:0] $end
$var wire 32 M ean [31:0] $end
$var wire 33 N ar [32:0] $end
$var wire 12 O af [11:0] $end
$var wire 32 P a [31:0] $end
$var parameter 32 Q ADC $end
$var parameter 32 R ADD $end
$var parameter 32 S AF $end
$var parameter 32 T AND $end
$var parameter 32 U CF $end
$var parameter 32 V CMP $end
$var parameter 32 W DF $end
$var parameter 32 X DIV $end
$var parameter 32 Y IF $end
$var parameter 32 Z INTERRUPT $end
$var parameter 32 [ MODRM $end
$var parameter 32 \ OF $end
$var parameter 32 ] OR $end
$var parameter 32 ^ PF $end
$var parameter 32 _ POP $end
$var parameter 32 ` PUSH $end
$var parameter 32 a RCL $end
$var parameter 32 b RCR $end
$var parameter 32 c ROL $end
$var parameter 32 d ROR $end
$var parameter 32 e RUN $end
$var parameter 32 f SAL $end
$var parameter 32 g SAR $end
$var parameter 32 h SBB $end
$var parameter 32 i SF $end
$var parameter 32 j SHL $end
$var parameter 32 k SHR $end
$var parameter 32 l SUB $end
$var parameter 32 m TF $end
$var parameter 32 n UNDEF $end
$var parameter 32 o WB $end
$var parameter 32 p XOR $end
$var parameter 32 q ZF $end
$var reg 3 r alu [2:0] $end
$var reg 1 s cp $end
$var reg 1 t cpen $end
$var reg 1 u cpm $end
$var reg 16 v cs [15:0] $end
$var reg 1 w dir $end
$var reg 16 x ds [15:0] $end
$var reg 32 y ea [31:0] $end
$var reg 32 z eax [31:0] $end
$var reg 32 { ebp [31:0] $end
$var reg 32 | ebx [31:0] $end
$var reg 32 } ecx [31:0] $end
$var reg 32 ~ edi [31:0] $end
$var reg 32 !" edx [31:0] $end
$var reg 32 "" eip [31:0] $end
$var reg 16 #" es [15:0] $end
$var reg 32 $" esi [31:0] $end
$var reg 32 %" esp [31:0] $end
$var reg 12 &" flags [11:0] $end
$var reg 8 '" interrupt [7:0] $end
$var reg 4 (" m [3:0] $end
$var reg 4 )" m1 [3:0] $end
$var reg 3 *" m2 [2:0] $end
$var reg 3 +" m3 [2:0] $end
$var reg 3 ," m4 [2:0] $end
$var reg 8 -" modrm [7:0] $end
$var reg 4 ." next [3:0] $end
$var reg 8 /" o [7:0] $end
$var reg 32 0" op1 [31:0] $end
$var reg 32 1" op2 [31:0] $end
$var reg 1 2" op66 $end
$var reg 1 3" op67 $end
$var reg 8 4" opcache [7:0] $end
$var reg 1 5" over $end
$var reg 2 6" rep [1:0] $end
$var reg 32 7" sgn [31:0] $end
$var reg 1 8" size $end
$var reg 16 9" ss [15:0] $end
$var reg 4 :" t [3:0] $end
$var reg 1 " w $end
$var reg 32 ;" wb [31:0] $end
$upscope $end
$upscope $end
$enddefinitions $end
$comment Show the parameter values. $end
$dumpall
b110 q
b110 p
b10 o
b111 n
b1000 m
b101 l
b101 k
b100 j
b111 i
b11 h
b111 g
b110 f
b0 e
b1 d
b0 c
b11 b
b10 a
b11 `
b100 _
b10 ^
b1 ]
b1011 \
b1 [
b110 Z
b1001 Y
b101 X
b1010 W
b111 V
b0 U
b100 T
b100 S
b0 R
b10 Q
$end
#0
$dumpvars
bx ;"
bx :"
bx 9"
x8"
bx 7"
bx 6"
x5"
bx 4"
x3"
x2"
bx 1"
bx 0"
bx /"
bx ."
bx -"
bx ,"
bx +"
bx *"
bx )"
bx ("
bx '"
bx &"
bx %"
bx $"
bx #"
bx ""
bx !"
bx ~
bx }
bx |
bx {
bx z
bx y
bx x
xw
bx v
xu
xt
xs
bx r
bx P
bx0x0x1x O
bx N
bx M
bx L
bx K
bx J
xI
xH
xG
xF
bx E
bx D
bx C
bx B
bx A
bx @
bx111 ?
bx >
x=
x<
x;
x:
x9
bx 8
17
x6
b1111111111111111 5
b0 4
b0 3
b0 2
b1111111111111111 1
b1111111111110000 0
b0 /
b0 .
b0 -
b0 ,
b0 +
b0 *
b0 )
b1111000000000000 (
0'
0&
0%
bx $
bx #
x"
bx !
$end
#5
1%
#10
0%
#15
1%
#20
b0 K
b0 J
b0 D
b0 C
b0 B
b0 A
b110110 E
b110110 @
b110110 !
b110110 8
bx000xx0x0x1x O
b11111111111111110000 $
b11111111111111110000 P
1;
b0 &"
b1111111111110001 L
b1111111111110000 ""
b0 x
b1111111111111111 9"
b1111000000000000 v
b1111111111111111 #"
b0 ~
b0 $"
b0 {
b0 %"
b0 !"
b0 }
b0 |
b0 >
b0 z
0s
b0 ("
b0 :"
0%
1&
#25
1%
#30
0%
#35
1%
#40
0%
0&
1'
#45
1%
#50
0%
#55
1%
#60
b1 E
b111 ?
b1 @
b1 !
b1 8
06
b11111111111111110001 $
b11111111111111110001 P
b1111111111111111 7"
15"
08"
1w
b110110 4"
1t
1u
b0 ,"
b0 +"
b0 *"
b0 )"
b0 ("
13"
12"
b1111111111110010 L
b1111111111110001 ""
b0 ."
0"
0%
1&
#65
1%
#70
0%
#75
1%
#80
0%
0&
#85
1%
#90
0%
#95
1%
#100
1:
b11111 ?
b110 @
b110 !
b110 8
19
0;
b11111111111111110010 $
b11111111111111110010 P
b0 r
b1 :"
18"
0w
b1 4"
b1 ("
b1111111111110011 L
b1111111111110010 ""
0%
1&
#105
1%
#110
0%
#115
1%
#120
0%
0&
#125
1%
#130
0%
#135
1%
#140
1F
0=
0<
1H
b1000110 O
0G
0I
b0 N
b11111111111111110011 $
b11111111111111110011 P
b1 M
b0 y
b0 1"
b0 0"
b1111111111110100 L
b1111111111110011 ""
b110 -"
0%
1&
#145
1%
#150
0%
#155
1%
#160
0%
0&
#165
1%
#170
0%
#175
1%
#180
b0 @
b0 !
b0 8
b11111111111111110100 $
b11111111111111110100 P
b1111111111110101 L
b1111111111110100 ""
0%
1&
#185
1%
#190
0%
#195
1%
#200
0%
0&
#205
1%
#210
0%
#215
1%
#220
b11111111111111111111111110010000 @
b10010000 !
b10010000 8
b11111111111111110101 $
b11111111111111110101 P
b1111111111110110 L
b1111111111110101 ""
b0 -"
0%
1&
#225
1%
#230
0%
#235
1%
#240
0%
0&
#245
1%
#250
0%
#255
1%
#260
b11111111111111111111111111101111 @
b11101111 !
b11101111 8
b11111111111111110110 $
b11111111111111110110 P
b10 )"
b1111111111110111 L
b1111111111110110 ""
b10010000 -"
0%
1&
#265
1%
#270
0%
#275
1%
#280
0%
0&
#285
1%
#290
0%
#295
1%
#300
b11111111111111111111111110111110 @
b10111110 !
b10111110 8
b11111111111111110111 $
b11111111111111110111 P
b11110000 M
b11101111 y
b1111111111111000 L
b1111111111110111 ""
b11 )"
0%
1&
#305
1%
#310
0%
#315
1%
#320
0%
0&
#325
1%
#330
0%
#335
1%
#340
bx K
bx J
bx D
bx C
bx B
bx A
bx @
bx !
bx 8
b11111111111111111000 $
b11111111111111111000 P
b1011111011110000 M
b1011111011101111 y
b1111111111111001 L
b1111111111111000 ""
b100 )"
0%
1&
#345
1%
#350
0%
#355
1%
#360
0%
0&
#365
1%
#370
0%
#375
1%
#380
b11111111111111111001 $
b11111111111111111001 P
bx M
bx y
b1111111111111010 L
b1111111111111001 ""
b101 )"
0%
1&
#385
1%
#390
0%
#395
1%
#400
0%
0&
#405
1%
#410
0%
#415
1%
#420
bx $
bx P
1s
b1111111111111011 L
b1111111111111010 ""
b0 )"
0%
1&
#425
1%
#430
0%
#435
1%
#440
0%
0&
#445
1%
#450
0%
#455
1%
#460
xF
x<
xH
x=
bx000xx0x0x1x O
xG
xI
bx N
b1010 )"
bx 1"
bx 0"
b1111111111111100 L
b1111111111111011 ""
bx -"
0%
1&
