32_furry/core.v
module core
(
    // --- УПРАВЛЯЮЩИЕ
    input               clock,      // 25Мгц
    input               rst_n,      // =0 Сброс процессора
    input               ce,         // =1 Активация чипа
    output              m0,         // Первый такт
    // --- ПАМЯТЬ
    output      [31:0]  a,          // Адрес в общей памяти
    input       [ 7:0]  i,          // Данные из памяти
    output reg  [ 7:0]  o,          // Данные в память
    output reg          w,          // Запись в память,
    // --- РЕГИСТРЫ
    output reg  [31:0]  eax,
    output reg  [31:0]  ebx,
    output reg  [31:0]  ecx,
    output reg  [31:0]  edx,
    output reg  [31:0]  esp,
    output reg  [31:0]  ebp,
    output reg  [31:0]  esi,
    output reg  [31:0]  edi,
    // --- СЕГМЕНТЫ
    output reg  [15:0]  es,
    output reg  [15:0]  cs,
    output reg  [15:0]  ss,
    output reg  [15:0]  ds,
    // --- УПРАВЛЯЮЩИЕ
    output reg  [31:0]  eip,
    output reg  [11:0]  flags,
    // --- ИНИЦИАЛИЗАЦИЯ
    input       [31:0]  _eax,
    input       [31:0]  _ebx,
    input       [31:0]  _ecx,
    input       [31:0]  _edx,
    input       [31:0]  _esp,
    input       [31:0]  _ebp,
    input       [31:0]  _esi,
    input       [31:0]  _edi,
    input       [15:0]  _es,
    input       [15:0]  _cs,
    input       [15:0]  _ss,
    input       [15:0]  _ds,
    input       [31:0]  _eip,
    input       [11:0]  _flags
);

assign a  = cp ? sgn*16 + ea : cs*16 + eip;
assign m0 = (m == 0 && t == RUN);

localparam
    RUN         = 0, // Исполнение
    MODRM       = 1, // Разбор операндов
    WB          = 2, // Запись результата
    PUSH        = 3, // Запись wb в стек
    POP         = 4, // Чтение из стека -> wb
    DIV         = 5, // Деление op1/op2
    INTERRUPT   = 6, // Вызов прерывания
    UNDEF       = 7; // Ошибка опкода

localparam ADD = 0, OR  = 1, ADC = 2, SBB  = 3, AND = 4, SUB = 5, XOR = 6, CMP = 7;
localparam ROL = 0, ROR = 1, RCL = 2, RCR  = 3, SHL = 4, SHR = 5, SAL = 6, SAR = 7;
localparam CF  = 0, PF  = 2, AF  = 4, ZF   = 6, SF  = 7, TF  = 8, IF  = 9, DF  = 10, OF = 11;

// -----------------------------------------------------
`define CPEN cp <= cpen; if (!cpen) begin m1 <= 0; t <= RUN; end
`define TERM {m, rep, over, op66, op67, sgn} <= ds;
// Если эта процедура является завершающей, так как переход идет на RUN
`define TERM_FN if (next == RUN && !m) `TERM
// Подготовка записи в 8 битный регистр
`define WR8(a)  {modrm[5:3], dir, size} <= {a, 2'b10}
`define WR16(a) {modrm[5:3], dir, size} <= {a, 2'b11}
// -----------------------------------------------------
reg         cp;                     // =1 Указатель на SGN:EA =0 Иначе CS:IP
reg         cpm;                    // =0 Устанавливается cp после MODRM
reg         size;                   // =1 16bit =0 8bit
reg         dir;                    // =0 rm,r; =1 r,rm
reg         cpen;                   // =0 То пропускает чтение операндов
reg         over;                   // =1 Сегмент переопределен
reg         intrc;                  // Предыдущее значение intr
reg [ 1:0]  rep;                    // Наличие REP:
reg [ 3:0]  t, next;                // Исполняемая команда (t) в данный момент
reg [ 3:0]  m, m1;                  // Фаза исполнения T (m), MODRM и субфаза
reg [ 2:0]  m2, m3, m4;             // Фаза исполнения WB, PUSH/POP
reg [ 2:0]  alu;                    // Функция АЛУ или сдвигов
reg [ 7:0]  modrm, sib, opcache;    // Кешированные значения
reg [ 7:0]  interrupt;              // Номер прерывания
reg [31:0]  sgn, ea;                // Выбранный SEGMENT:EA
reg [31:0]  op1, op2, wb, t16;      // Операнды; wb-что записывать
reg         op66, op67;             // Сужение битности 32 до 16 если =1
// -----------------------------------------------------
assign      m0 = (t == RUN && m == 0);
wire        c0 = m0 && {over, rep} == 3'b0;
wire [7:0]  opcode = m || t ? opcache : i;
// -----------------------------------------------------
wire [255:0] u20 = {edi, esi, ebp, esp, ebx, edx, ecx, eax};
// ----
wire [ 31:0] r20 = u20 >> {i[2:0], 5'b0};
wire [ 31:0] r53 = u20 >> {i[5:3], 5'b0};
wire [  7:0] s20 = u20 >> {i[1:0], 1'b0, i[2], 3'b0};
wire [  7:0] s53 = u20 >> {i[4:3], 1'b0, i[5], 3'b0};
// ----
wire [ 31:0] i20 = size ? (op66 ? r20[15:0] : r20) : s20;
wire [ 31:0] i53 = size ? (op66 ? r53[15:0] : r53) : s53;
// ----
wire [ 31:0] sign = {{24{i[7]}}, i};
wire [ 31:0] eipn = eip + 1'b1;
wire [ 31:0] ean  = ea  + 1'b1;
// -----------------------------------------------------
wire [4:0]  top = size ? (op66 ? 15 : 31) : 7;
wire [32:0] ar =
    alu == ADD ? op1 + op2 :
    alu == ADC ? op1 + op2 + flags[CF] :
    alu == SBB ? op1 - op2 - flags[CF] :
    alu == AND ? op1 & op2 :
    alu == XOR ? op1 ^ op2 :
    alu == OR  ? op1 | op2 : op1 - op2;

wire isa    = alu == ADD || alu == ADC;
wire isl    = alu != AND && alu != OR && alu != XOR;
wire new_o  = (op1[top] ^ op2[top] ^ isa) & (op1[top] ^ ar[top]);
wire new_s  = ar[top];
wire new_z  = 0 == (size ? ar[15:0] : ar[7:0]);
wire new_a  = op1[4] ^ op2[4] ^ ar[4];
wire new_p  = ~^ar[7:0];
wire new_c  = ar[top + 1];

wire [11:0] af = {new_o & isl, flags[10:8], new_s, new_z, 1'b0, new_a & isl, 1'b0, new_p, 1'b1, new_c & isl};
// -----------------------------------------------------

always @(posedge clock)
// Сброс процессора
if (rst_n == 0) begin

    t       <= RUN;
    m       <= 0;
    cp      <= 0;
    op66    <= 0;
    op67    <= 0;
    modrm   <= 0;

    // Копирование первоначальных значений при сбросе
    eax     <= _eax; ebx <= _ebx; ecx <= _ecx; edx <= _edx;
    esp     <= _esp; ebp <= _ebp; esi <= _esi; edi <= _edi;

    es      <= _es;
    cs      <= _cs;
    ss      <= _ss;
    ds      <= _ds;

    eip     <= _eip;
    flags   <= _flags;

end
// Запуск выполнения команд процессора
else if (ce) begin

    w <= 0;

    // Очистить управляющие регистры в начале инструкции
    if (m0) begin

        next    <= RUN;
        eip     <= eipn;
        op1     <= 0;
        op2     <= 0;
        alu     <= i[5:3];
        m       <= 1;
        m1      <= 0;
        m2      <= 0;
        m3      <= 0;
        m4      <= 0;
        cpm     <= 1;
        cpen    <= 1;
        opcache <= i;
        dir     <= i[1];
        size    <= i[0];

        if (c0) sgn <= ds;

    end

    case (t)

    // ИСПОЛНЕНИЕ ИНСТРУКЦИИ
    RUN: casex (opcode)

        // ### ALU-операции с операндами ModRM [3T+]
        8'b00xxx0xx: case (m)

            0: begin t <= MODRM; alu <= opcode[5:3]; end
            1: begin

                m     <= 0;
                t     <= alu == CMP ? RUN : WB;
                wb    <= ar;
                flags <= af;

                if (alu == CMP) `TERM;

            end

        endcase

        // ### MOV rb, imm8
        8'b10110xxx: case (m)

            0: begin `WR8(opcode[2:0]); end
            1: begin m <= 0; t <= WB; wb <= i; eip <= eipn; end

        endcase

        // ### MOV rv, imm [4T/6T]
        8'b10111xxx: case (m)

            0: begin `WR16(opcode[2:0]); end
            1: begin eip <= eipn; wb        <= i; m <= 2; end
            2: begin eip <= eipn; wb[15:8]  <= i; m <= op66 ? 0 : 3; if (op66) t <= WB; end
            3: begin eip <= eipn; wb[23:16] <= i; m <= 4; end
            4: begin eip <= eipn; wb[31:24] <= i; m <= 0; t <= WB; end

        endcase

        // ### Префикс ES/CS/SS/DS [1T]
        8'b00100110: begin m <= 0; over <= 1; sgn <= es; end
        8'b00101110: begin m <= 0; over <= 1; sgn <= cs; end
        8'b00110110: begin m <= 0; over <= 1; sgn <= ss; end
        8'b00111110: begin m <= 0; over <= 1; sgn <= ds; end

        // ### Opsize, Adsize
        8'b01100110: begin m <= 0; op66 <= ~op66; end
        8'b01100111: begin m <= 0; op67 <= ~op67; end

        // ### REPNZ, REPZ [1T]
        8'b1111001x: begin m <= 0; rep <= i[1:0]; end

    endcase

    // СЧИТЫВАНИЕ ОПЕРАНДОВ ИЗ РЕГИСТРОВ ИЛИ ИЗ ПАМЯТИ
    MODRM: case (m1)

        // Разбор 16/32 эффективного адреса и регистров при необходимости
        0: begin

            modrm   <= i;
            eip     <= eipn;
            op1     <= dir ? i53 : i20;
            op2     <= dir ? i20 : i53;

            if (op67) begin


                // Вычислить эффективный 16-битный адрес
                case (i[2:0])
                3'b000: ea <= ebx[15:0] + esi[15:0];
                3'b001: ea <= ebx[15:0] + edi[15:0];
                3'b010: ea <= ebp[15:0] + esi[15:0];
                3'b011: ea <= ebp[15:0] + edi[15:0];
                3'b100: ea <= esi[15:0];
                3'b101: ea <= edi[15:0];
                3'b110: ea <= i[7:6] ? ebp[15:0] : 0;
                3'b111: ea <= ebx[15:0];
                endcase

                // Возможные 16-битные смещения
                casex (i)
                8'b00_xxx_110: begin m1 <= 2; end           // OFFSET16
                8'b00_xxx_xxx: begin m1 <= 6; `CPEN; end    // Читать операнд
                8'b01_xxx_xxx: begin m1 <= 1; end           // +Смещение 8 бит
                8'b10_xxx_xxx: begin m1 <= 2; end           // +Смещение 16 бит
                8'b11_xxx_xxx: begin m1 <= 0; t <= RUN; end // Регистры. Вернуться к RUN
                endcase

                if (!over && ((^i[7:6] && i[2:0] == 3'b110) || i[2:1] == 2'b01)) sgn <= ss;

            end else begin

                ea <= i20;

                // Эффективный 32-х битный адрес
                casex (i)
                8'b00_xxx_100: begin m1 <= 10; end          // SIB
                8'b00_xxx_101: begin ea <= 0; m2 <= 2;  end // A32
                8'b01_xxx_101: begin m1 <= 1; if (!over) sgn <= ss; end
                8'b10_xxx_101: begin m1 <= 2; if (!over) sgn <= ss; end
                8'b01_xxx_xxx: begin m1 <= 1; end           // +D8
                8'b10_xxx_xxx: begin m1 <= 2; end           // +32
                8'b11_xxx_xxx: begin m1 <= 0; t <= RUN; end
                endcase

            end

        end

        // DISP8
        1: begin m1 <= 4; eip <= eipn; ea <= ea + sign; `CPEN; end

        // DISP16/32
        2: begin m1 <= 3; eip <= eipn; ea <= ea + {8'b0, i}; end
        3: begin m1 <= 4; eip <= eipn; ea <= ea + {i, 8'b0}; if (!op67) m1 <= 4; else begin `CPEN; end end
        4: begin m1 <= 5; eip <= eipn; ea <= ea + {i, 16'b0}; end
        5: begin m1 <= 0; eip <= eipn; ea <= ea + {i, 24'b0}; `CPEN; end

        // Читать 8-битный операнд
        6: begin

            if (dir) op2 <= i; else op1 <= i;
            if (size) begin m1 <= 5; ea <= ean; end
            else      begin m1 <= 0; cp <= cpm; t <= RUN; end

        end

        // Читать 16-битный операнд
        7: begin

            if (dir) op2[15:8] <= i; else op1[15:8] <= i;

            if (!op67) m1 <= 8;
            else begin

                t  <= RUN;
                m1 <= 0;
                ea <= ea - 1;
                cp <= cpm;

            end

        end

        // Читать операнд 32-х бит
        8: begin m1 <= 9; if (dir) op2[23:16] <= i; else op1[23:16] <= i; end
        9: begin

            if (dir) op2[31:24] <= i; else op1[31:24] <= i;

            t  <= RUN;
            m1 <= 0;
            ea <= ea - 3;
            cp <= cpm;

        end

        // SIB
        10: begin end

    endcase

    // [1T,2-3T] ЗАПИСЬ РЕЗУЛЬТАТОВ WB,DIR,SIZE,MODRM В ПАМЯТЬ/РЕГИСТРЫ
    WB: case (m2)

        // Записать в регистры, если это явно указано
        0: if (dir || modrm[7:6] == 2'b11) begin

            t  <= next;
            cp <= 0;

            casex ({op66, size, dir ? modrm[5:3] : modrm[2:0]})
            // 8
            5'bx0_000: eax[ 7:0] <= wb[7:0];
            5'bx0_001: ecx[ 7:0] <= wb[7:0];
            5'bx0_010: edx[ 7:0] <= wb[7:0];
            5'bx0_011: ebx[ 7:0] <= wb[7:0];
            5'bx0_100: eax[15:8] <= wb[7:0];
            5'bx0_101: ecx[15:8] <= wb[7:0];
            5'bx0_110: edx[15:8] <= wb[7:0];
            5'bx0_111: ebx[15:8] <= wb[7:0];
            // 32
            5'b01_000: eax <= wb;
            5'b01_001: ecx <= wb;
            5'b01_010: edx <= wb;
            5'b01_011: ebx <= wb;
            5'b01_100: esp <= wb;
            5'b01_101: ebp <= wb;
            5'b01_110: esi <= wb;
            5'b01_111: edi <= wb;
            // 16
            5'b11_000: eax[15:0] <= wb[15:0];
            5'b11_001: ecx[15:0] <= wb[15:0];
            5'b11_010: edx[15:0] <= wb[15:0];
            5'b11_011: ebx[15:0] <= wb[15:0];
            5'b11_100: esp[15:0] <= wb[15:0];
            5'b11_101: ebp[15:0] <= wb[15:0];
            5'b11_110: esi[15:0] <= wb[15:0];
            5'b11_111: edi[15:0] <= wb[15:0];
            endcase

            `TERM_FN;

        end
        // Либо записать в память младший байт wb
        else begin w <= 1; cp <= 1; m2 <= 1; o <= wb[7:0]; end
        // Старший байт нижнего слова
        1: begin

            o  <= wb[15:8];
            w  <= size;
            ea <= ean;

            if (size && !op66) m2 <= 2;
            else if (!size) begin m2 <= 0; cp <= 0; t <= next; `TERM_FN; end

        end
        // Верхнее слово
        2: begin m2 <= 3; w <= 1; o <= wb[23:16]; end
        3: begin m2 <= 4; w <= 1; o <= wb[31:24]; end
        4: begin m2 <= 0; cp <= 0; t <= next; `TERM_FN; end

    endcase // Завершение m2

    // [3T] ВЫГРУЗКА WB -> В СТЕК
    PUSH: case (m3)
    0: begin

        w  <= 1; o   <= wb[ 7:0];
        cp <= 1; esp <= esp - 2; sgn <= ss;
        m3 <= 1; ea  <= esp - 2;

    end
    1: begin o <= wb[15:8];  m3 <= op66 ? 4 : 2; ea <= ean; w <= 1; end
    2: begin o <= wb[23:16]; m3 <= 3; ea <= ean; w <= 1; end
    3: begin o <= wb[31:24]; m3 <= 4; ea <= ean; w <= 1; end
    4: begin `TERM_FN;       m3 <= 0; cp <= 0; t <= next; end
    endcase

    // [3T] ЗАГРУЗКА ИЗ СТЕКА -> WB
    POP: case (m3)
    0: begin m3 <= 1; cp <= 1; sgn <= ss; ea <= esp; esp <= esp + 2; end
    1: begin m3 <= op66 ? 4 : 2; wb <= i; ea <= ean; end
    2: begin m3 <= 3; wb[15:8]  <= i; ea <= ean; end
    3: begin m3 <= 4; wb[23:16] <= i; ea <= ean; end
    4: begin

        t  <= next;
        m3 <= 0;
        cp <= 0;

        if (op66) wb[15:8] <= i; else wb[31:24] <= i;

        `TERM_FN;

    end

    endcase

    // [17T] ВЫЗОВ ПРОЦЕДУРЫ INTERRUPT
    INTERRUPT: case (m4)
    0: begin m4 <= 1; t  <= PUSH; wb <= {4'hF, flags}; next <= INTERRUPT; end
    1: begin m4 <= 2; t  <= PUSH; wb <= cs; end
    2: begin m4 <= 3; t  <= PUSH; wb <= eip; end
    3: begin m4 <= 4; ea <= {interrupt, 2'b00}; sgn <= 0; cp <= 1; end
    4: begin m4 <= 5; eip[ 7:0] <= i; ea <= ean; end
    5: begin m4 <= 6; eip[15:8] <= i; ea <= ean; end
    6: begin m4 <= 7; cs[ 7:0]  <= i; ea <= ean; end
    7: begin m4 <= 0; cs[15:8]  <= i; cp <= 0; t <= RUN; flags[IF] <= 1'b0; m <= 0; `TERM; end
    endcase

    endcase

end

endmodule

32_furry/tb.v
`timescale 10ns / 1ns
module tb;

// --------------------------------
reg clock_25 = 0, clock_100 = 0, rst_n = 0;
// --------------------------------
always #2.0 clock_25  = ~clock_25;
always #0.5 clock_100 = ~clock_100;
// -----------------------------------------------------------------------------
reg [7:0] mem[1048576];
// -----------------------------------------------------------------------------
initial begin #4.0 rst_n = 1; #1000 $finish; end
initial begin $dumpfile("tb.vcd"); $dumpvars(0, tb); end
initial begin $readmemh("tb.hex", mem, 20'hFFFF0); end
// -----------------------------------------------------------------------------
reg  [31:0] a_;
wire [31:0] a;
wire [ 7:0] i = mem[a_[19:0]];
wire [ 7:0] o;
wire        w;
// -----------------------------------------------------------------------------
always @(negedge clock_25) begin a_ <= a; if (w) mem[a[19:0]] <= o; end
// -----------------------------------------------------------------------------

core C1
(
    .clock  (clock_25),
    .rst_n  (rst_n),
    .ce     (1'b1),
    // Подключение к контроллеру памяти
    .a      (a),
    .i      (i),
    .o      (o),
    .w      (w),
    // Первичное значение регистров
    ._eax   (32'h0000),
    ._ebx   (32'h0000),
    ._ecx   (32'h0000),
    ._edx   (32'h0000),
    ._esp   (32'h0000),
    ._ebp   (32'h0000),
    ._esi   (32'h0000),
    ._edi   (32'h0000),
    ._es    (16'hFFFF),
    ._cs    (16'hF000),
    ._ss    (16'hFFFF),
    ._ds    (16'h0000),
    ._eip   (32'hFFF0),
    ._flags (12'b0000_0000_0000)
);

endmodule

32_furry/tb.vcd
$date
	Fri Mar 13 14:33:23 2026
$end
$version
	Icarus Verilog
$end
$timescale
	1ns
$end
$scope module tb $end
$var wire 8 ! i [7:0] $end
$var wire 1 " w $end
$var wire 8 # o [7:0] $end
$var wire 32 $ a [31:0] $end
$var reg 32 % a_ [31:0] $end
$var reg 1 & clock_100 $end
$var reg 1 ' clock_25 $end
$var reg 1 ( rst_n $end
$scope module C1 $end
$var wire 16 ) _cs [15:0] $end
$var wire 16 * _ds [15:0] $end
$var wire 32 + _eax [31:0] $end
$var wire 32 , _ebp [31:0] $end
$var wire 32 - _ebx [31:0] $end
$var wire 32 . _ecx [31:0] $end
$var wire 32 / _edi [31:0] $end
$var wire 32 0 _edx [31:0] $end
$var wire 32 1 _eip [31:0] $end
$var wire 16 2 _es [15:0] $end
$var wire 32 3 _esi [31:0] $end
$var wire 32 4 _esp [31:0] $end
$var wire 12 5 _flags [11:0] $end
$var wire 16 6 _ss [15:0] $end
$var wire 1 7 c0 $end
$var wire 1 8 ce $end
$var wire 1 ' clock $end
$var wire 8 9 i [7:0] $end
$var wire 1 : isa $end
$var wire 1 ; isl $end
$var wire 1 < m0 $end
$var wire 1 = new_a $end
$var wire 1 > new_o $end
$var wire 1 ( rst_n $end
$var wire 256 ? u20 [255:0] $end
$var wire 5 @ top [4:0] $end
$var wire 32 A sign [31:0] $end
$var wire 8 B s53 [7:0] $end
$var wire 8 C s20 [7:0] $end
$var wire 32 D r53 [31:0] $end
$var wire 32 E r20 [31:0] $end
$var wire 8 F opcode [7:0] $end
$var wire 1 G new_z $end
$var wire 1 H new_s $end
$var wire 1 I new_p $end
$var wire 1 J new_c $end
$var wire 32 K i53 [31:0] $end
$var wire 32 L i20 [31:0] $end
$var wire 32 M eipn [31:0] $end
$var wire 32 N ean [31:0] $end
$var wire 33 O ar [32:0] $end
$var wire 12 P af [11:0] $end
$var wire 32 Q a [31:0] $end
$var parameter 32 R ADC $end
$var parameter 32 S ADD $end
$var parameter 32 T AF $end
$var parameter 32 U AND $end
$var parameter 32 V CF $end
$var parameter 32 W CMP $end
$var parameter 32 X DF $end
$var parameter 32 Y DIV $end
$var parameter 32 Z IF $end
$var parameter 32 [ INTERRUPT $end
$var parameter 32 \ MODRM $end
$var parameter 32 ] OF $end
$var parameter 32 ^ OR $end
$var parameter 32 _ PF $end
$var parameter 32 ` POP $end
$var parameter 32 a PUSH $end
$var parameter 32 b RCL $end
$var parameter 32 c RCR $end
$var parameter 32 d ROL $end
$var parameter 32 e ROR $end
$var parameter 32 f RUN $end
$var parameter 32 g SAL $end
$var parameter 32 h SAR $end
$var parameter 32 i SBB $end
$var parameter 32 j SF $end
$var parameter 32 k SHL $end
$var parameter 32 l SHR $end
$var parameter 32 m SUB $end
$var parameter 32 n TF $end
$var parameter 32 o UNDEF $end
$var parameter 32 p WB $end
$var parameter 32 q XOR $end
$var parameter 32 r ZF $end
$var reg 3 s alu [2:0] $end
$var reg 1 t cp $end
$var reg 1 u cpen $end
$var reg 1 v cpm $end
$var reg 16 w cs [15:0] $end
$var reg 1 x dir $end
$var reg 16 y ds [15:0] $end
$var reg 32 z ea [31:0] $end
$var reg 32 { eax [31:0] $end
$var reg 32 | ebp [31:0] $end
$var reg 32 } ebx [31:0] $end
$var reg 32 ~ ecx [31:0] $end
$var reg 32 !" edi [31:0] $end
$var reg 32 "" edx [31:0] $end
$var reg 32 #" eip [31:0] $end
$var reg 16 $" es [15:0] $end
$var reg 32 %" esi [31:0] $end
$var reg 32 &" esp [31:0] $end
$var reg 12 '" flags [11:0] $end
$var reg 8 (" interrupt [7:0] $end
$var reg 4 )" m [3:0] $end
$var reg 4 *" m1 [3:0] $end
$var reg 3 +" m2 [2:0] $end
$var reg 3 ," m3 [2:0] $end
$var reg 3 -" m4 [2:0] $end
$var reg 8 ." modrm [7:0] $end
$var reg 4 /" next [3:0] $end
$var reg 8 0" o [7:0] $end
$var reg 32 1" op1 [31:0] $end
$var reg 32 2" op2 [31:0] $end
$var reg 1 3" op66 $end
$var reg 1 4" op67 $end
$var reg 8 5" opcache [7:0] $end
$var reg 1 6" over $end
$var reg 2 7" rep [1:0] $end
$var reg 32 8" sgn [31:0] $end
$var reg 1 9" size $end
$var reg 16 :" ss [15:0] $end
$var reg 4 ;" t [3:0] $end
$var reg 1 " w $end
$var reg 32 <" wb [31:0] $end
$upscope $end
$upscope $end
$enddefinitions $end
$comment Show the parameter values. $end
$dumpall
b110 r
b110 q
b10 p
b111 o
b1000 n
b101 m
b101 l
b100 k
b111 j
b11 i
b111 h
b110 g
b0 f
b1 e
b0 d
b11 c
b10 b
b11 a
b100 `
b10 _
b1 ^
b1011 ]
b1 \
b110 [
b1001 Z
b101 Y
b1010 X
b111 W
b0 V
b100 U
b100 T
b0 S
b10 R
$end
#0
$dumpvars
bx <"
bx ;"
bx :"
x9"
bx 8"
bx 7"
x6"
bx 5"
x4"
x3"
bx 2"
bx 1"
bx 0"
bx /"
bx ."
bx -"
bx ,"
bx +"
bx *"
bx )"
bx ("
bx '"
bx &"
bx %"
bx $"
bx #"
bx ""
bx !"
bx ~
bx }
bx |
bx {
bx z
bx y
xx
bx w
xv
xu
xt
bx s
bx Q
bx0x0x1x P
bx O
bx N
bx M
bx L
bx K
xJ
xI
xH
xG
bx F
bx E
bx D
bx C
bx B
bx A
bx111 @
bx ?
x>
x=
x<
x;
x:
bx 9
18
x7
b1111111111111111 6
b0 5
b0 4
b0 3
b1111111111111111 2
b1111111111110000 1
b0 0
b0 /
b0 .
b0 -
b0 ,
b0 +
b0 *
b1111000000000000 )
0(
0'
0&
bx %
bx $
bx #
x"
bx !
$end
#5
1&
#10
0&
#15
1&
#20
bx000xx0x0x1x P
b11111111111111110000 $
b11111111111111110000 Q
1<
b0 '"
b1111111111110001 M
b1111111111110000 #"
b0 y
b1111111111111111 :"
b1111000000000000 w
b1111111111111111 $"
b0 !"
b0 %"
b0 |
b0 &"
b0 ""
b0 ~
b0 }
b0 ?
b0 {
b0 ."
04"
03"
0t
b0 )"
b0 ;"
0&
1'
#25
1&
#30
0&
#35
1&
#40
b0 L
b0 K
b0 E
b0 D
b0 C
b0 B
b10111000 F
b11111111111111111111111110111000 A
b10111000 !
b10111000 9
b11111111111111110000 %
0&
0'
1(
#45
1&
#50
0&
#55
1&
#60
1G
0=
0>
1I
b1000110 P
0H
0J
b0 O
b11111 @
07
1;
0<
0:
b11111111111111110001 $
b11111111111111110001 Q
19"
1x
b10111000 5"
1u
1v
b0 -"
b0 ,"
b0 +"
b0 *"
b1 )"
b111 s
b0 2"
b0 1"
b1111111111110010 M
b1111111111110001 #"
b0 /"
0"
0&
1'
#65
1&
#70
0&
#75
1&
#80
b11111111111111111111111111101111 A
b11101111 !
b11101111 9
b11111111111111110001 %
0&
0'
#85
1&
#90
0&
#95
1&
#100
b11111111111111110010 $
b11111111111111110010 Q
b10 )"
b11101111 <"
b1111111111110011 M
b1111111111110010 #"
0&
1'
#105
1&
#110
0&
#115
1&
#120
b11111111111111111111111110111110 A
b10111110 !
b10111110 9
b11111111111111110010 %
0&
0'
#125
1&
#130
0&
#135
1&
#140
b11111111111111110011 $
b11111111111111110011 Q
b11 )"
b1011111011101111 <"
b1111111111110100 M
b1111111111110011 #"
0&
1'
#145
1&
#150
0&
#155
1&
#160
b11111111111111111111111110101101 A
b10101101 !
b10101101 9
b11111111111111110011 %
0&
0'
#165
1&
#170
0&
#175
1&
#180
b11111111111111110100 $
b11111111111111110100 Q
b100 )"
b101011011011111011101111 <"
b1111111111110101 M
b1111111111110100 #"
0&
1'
#185
1&
#190
0&
#195
1&
#200
b11111111111111111111111111011110 A
b11011110 !
b11011110 9
b11111111111111110100 %
0&
0'
#205
1&
#210
0&
#215
1&
#220
b11111111111111110101 $
b11111111111111110101 Q
b10 ;"
b0 )"
b11011110101011011011111011101111 <"
b1111111111110110 M
b1111111111110101 #"
0&
1'
#225
1&
#230
0&
#235
1&
#240
b1100110 A
b1100110 !
b1100110 9
b11111111111111110101 %
0&
0'
#245
1&
#250
0&
#255
1&
#260
b1100110 F
17
b10111110 B
1<
b0 7"
06"
b0 8"
b11011110101011011011111011101111 ?
b11011110101011011011111011101111 {
b0 ;"
0&
1'
#265
1&
#270
0&
#275
1&
#280
0&
0'
#285
1&
#290
0&
#295
1&
#300
b111 @
0;
b10111110 K
b11111111111111110110 $
b11111111111111110110 Q
13"
09"
b1100110 5"
b0 )"
b100 s
b1111111111110111 M
b1111111111110110 #"
0&
1'
#305
1&
#310
0&
#315
1&
#320
b11101111 L
b0 K
b11011110101011011011111011101111 E
b11101111 C
b0 B
b10111000 F
b11111111111111111111111110111000 A
b10111000 !
b10111000 9
b11111111111111110110 %
0&
0'
#325
1&
#330
0&
#335
1&
#340
b1111 @
07
1;
b1011111011101111 L
0<
b11111111111111110111 $
b11111111111111110111 Q
19"
1x
b10111000 5"
b1 )"
b111 s
b1111111111111000 M
b1111111111110111 #"
0&
1'
#345
1&
#350
0&
#355
1&
#360
b0 L
b0 E
b0 C
b11111111111111111111111111011110 A
b11011110 !
b11011110 9
b11111111111111110111 %
0&
0'
#365
1&
#370
0&
#375
1&
#380
b11111111111111111000 $
b11111111111111111000 Q
b10 )"
b11011110 <"
b1111111111111001 M
b1111111111111000 #"
0&
1'
#385
1&
#390
0&
#395
1&
#400
b11111111111111111111111111011010 A
b11011010 !
b11011010 9
b11111111111111111000 %
0&
0'
#405
1&
#410
0&
#415
1&
#420
b11111111111111111001 $
b11111111111111111001 Q
b10 ;"
b0 )"
b1101101011011110 <"
b1111111111111010 M
b1111111111111001 #"
0&
1'
#425
1&
#430
0&
#435
1&
#440
b10111110 B
b1100110 A
b1100110 !
b1100110 9
b11111111111111111001 %
0&
0'
#445
1&
#450
0&
#455
1&
#460
b11111 @
17
b1100110 F
b11011010 B
1<
03"
b11011110101011011101101011011110 ?
b11011110101011011101101011011110 {
b0 ;"
0&
1'
#465
1&
#470
0&
#475
1&
#480
0&
0'
#485
1&
#490
0&
#495
1&
#500
b111 @
0;
b11011010 K
b11111111111111111010 $
b11111111111111111010 Q
13"
09"
b1100110 5"
b0 )"
b100 s
b1111111111111011 M
b1111111111111010 #"
0&
1'
#505
1&
#510
0&
#515
1&
#520
b0 K
b0 B
b10111010 F
b11111111111111111111111110111010 A
b10111010 !
b10111010 9
b11111111111111111010 %
0&
0'
#525
1&
#530
0&
#535
1&
#540
b1111 @
07
1;
0<
b11111111111111111011 $
b11111111111111111011 Q
b10000 ."
19"
b10111010 5"
b1 )"
b111 s
b1111111111111100 M
b1111111111111011 #"
0&
1'
#545
1&
#550
0&
#555
1&
#560
b1101 A
b1101 !
b1101 9
b11111111111111111011 %
0&
0'
#565
1&
#570
0&
#575
1&
#580
b11111111111111111100 $
b11111111111111111100 Q
b10 )"
b1101 <"
b1111111111111101 M
b1111111111111100 #"
0&
1'
#585
1&
#590
0&
#595
1&
#600
b1101101011011110 L
b11011110101011011101101011011110 E
b11011110 C
b11111111111111111111111111110000 A
b11110000 !
b11110000 9
b11111111111111111100 %
0&
0'
#605
1&
#610
0&
#615
1&
#620
b11111111111111111101 $
b11111111111111111101 Q
b10 ;"
b0 )"
b1111000000001101 <"
b1111111111111110 M
b1111111111111101 #"
0&
1'
#625
1&
#630
0&
#635
1&
#640
b11111111111111111111111110111000 A
b10111000 !
b10111000 9
b11111111111111111101 %
0&
0'
#645
1&
#650
0&
#655
1&
#660
b11111 @
b11011110101011011101101011011110 L
17
b10111000 F
1<
03"
b11110000000011010000000000000000000000000000000011011110101011011101101011011110 ?
b1111000000001101 ""
b0 ;"
0&
1'
#665
1&
#670
0&
#675
1&
#680
0&
0'
#685
1&
#690
0&
#695
1&
#700
07
0<
b11111111111111111110 $
b11111111111111111110 Q
b0 ."
19"
1x
b10111000 5"
b1 )"
b1111111111111111 M
b1111111111111110 #"
0&
1'
#705
1&
#710
0&
#715
1&
#720
b0 L
b1111000000001101 K
b0 E
b1111000000001101 D
b11011010 C
b1101 B
b10100 A
b10100 !
b10100 9
b11111111111111111110 %
0&
0'
#725
1&
#730
0&
#735
1&
#740
b11111111111111111111 $
b11111111111111111111 Q
b10 )"
b10100 <"
b10000000000000000 M
b1111111111111111 #"
0&
1'
#745
1&
#750
0&
#755
1&
#760
b11011110101011011101101011011110 L
b11011110101011011101101011011110 K
b11011110101011011101101011011110 E
b11011110101011011101101011011110 D
b11011110 C
b11011110 B
b0 A
b0 !
b0 9
b11111111111111111111 %
0&
0'
#765
1&
#770
0&
#775
1&
#780
b100000000000000000000 $
b100000000000000000000 Q
b11 )"
b10000000000000001 M
b10000000000000000 #"
0&
1'
#785
1&
#790
0&
#795
1&
#800
bx L
bx K
bx E
bx D
bx C
bx B
bx A
bx !
bx 9
b100000000000000000000 %
0&
0'
#805
1&
#810
0&
#815
1&
#820
b100000000000000000001 $
b100000000000000000001 Q
b100 )"
b0xxxxxxxx0000000000010100 <"
b10000000000000010 M
b10000000000000001 #"
0&
1'
#825
1&
#830
0&
#835
1&
#840
b100000000000000000001 %
0&
0'
#845
1&
#850
0&
#855
1&
#860
b100000000000000000010 $
b100000000000000000010 Q
b10 ;"
b0 )"
bx0000000000010100 <"
b10000000000000011 M
b10000000000000010 #"
0&
1'
#865
1&
#870
0&
